src/ami_lib_next.py
ami_lib_next-0.1.0.dist-info/METADATA
ami_lib_next-0.1.0.dist-info/WHEEL
ami_lib_next-0.1.0.dist-info/RECORD
